multisphere/__init__.py
multisphere/multisphere_datatypes.py
multisphere/multisphere_io.py
multisphere/multisphere_reconstruction.py
multisphere/multisphere_reconstruction_helpers.py
multisphere/multisphere_utils.py
multisphere/multisphere_visualisation.py
multisphere/multisphere_voxel_processing.py
multisphere-1.0.0.dist-info/licenses/LICENSE
multisphere-1.0.0.dist-info/METADATA
multisphere-1.0.0.dist-info/WHEEL
multisphere-1.0.0.dist-info/top_level.txt
multisphere-1.0.0.dist-info/RECORD
