Metadata-Version: 2.4
Name: multisphere
Version: 1.0.0
Summary: Multisphere representations of mesh and voxel geometries for DEM simulations
Author-email: Felix Buchele <felix.buchele@fau.de>
License: GNU GPL 3.0
Project-URL: Homepage, https://github.com/FelixBuchele/multisphere
Project-URL: Source, https://github.com/FelixBuchele/multisphere
Project-URL: Issues, https://github.com/FelixBuchele/multisphere/issues
Classifier: Programming Language :: Python :: 3
Classifier: Programming Language :: Python :: 3.9
Classifier: Programming Language :: Python :: 3.10
Classifier: Programming Language :: Python :: 3.11
Classifier: License :: OSI Approved :: GNU General Public License v3 (GPLv3)
Classifier: Operating System :: OS Independent
Requires-Python: >=3.9
License-File: LICENSE
Requires-Dist: numpy
Requires-Dist: scipy
Requires-Dist: scikit-image
Requires-Dist: trimesh
Provides-Extra: viz
Requires-Dist: pyvista; extra == "viz"
Provides-Extra: boolean
Requires-Dist: manifold3d; extra == "boolean"
Provides-Extra: full
Requires-Dist: pyvista; extra == "full"
Requires-Dist: manifold3d; extra == "full"
Dynamic: license-file
